cddm/__init__.py
cddm/_core_nb.py
cddm/_sim_nb.py
cddm/avg.py
cddm/cddm.ini
cddm/conf.py
cddm/core.py
cddm/decorators.py
cddm/fft.py
cddm/map.py
cddm/multitau.py
cddm/norm.py
cddm/print_tools.py
cddm/sim.py
cddm/video.py
cddm/viewer.py
cddm/window.py
cddm/test/__init__.py
cddm/test/test_conf.py
cddm/test/test_core.py
cddm/test/test_fft.py
cddm/test/test_map.py
cddm/test/test_multitau.py
cddm/test/test_numba.py
cddm/test/test_print_tools.py
cddm/test/test_sim.py
cddm/test/test_video.py
cddm/test/test_window.py
examples/__init__.py
examples/auto_correlate.py
examples/auto_correlate_multi.py
examples/conf.py
examples/cross_correlate_error.py
examples/cross_correlate_k_fit.py
examples/cross_correlate_multi_live.py
examples/cross_correlate_multi_masked.py
examples/cross_correlate_multi_subtracted.py
examples/dual_video_simulator.py
examples/mask_array.py
examples/show_live.py
examples/video_simulator.py
examples/paper/__init__.py
examples/paper/auto_correlate_error.py
examples/paper/auto_correlate_fast.py
examples/paper/auto_correlate_fast_error.py
examples/paper/auto_correlate_full.py
examples/paper/auto_correlate_random.py
examples/paper/auto_correlate_random_error.py
examples/paper/auto_correlate_standard.py
examples/paper/auto_correlate_standard_error.py
examples/paper/conf.py
examples/paper/correlate_k_fit.py
examples/paper/correlate_spectral_fit.py
examples/paper/cross_correlate.py
examples/paper/cross_correlate_error.py
examples/paper/cross_correlate_multi_live.py
examples/paper/error_plot.py
examples/paper/form_factor.py
examples/paper/plot_average.py
examples/paper/plot_fit_method.py
examples/paper/plot_fit_norm.py
examples/paper/plot_fit_norm2.py
examples/paper/plot_fit_norm3.py
examples/paper/simple_video/__init__.py
examples/paper/simple_video/conf.py
examples/paper/simple_video/dual_video.py
examples/paper/simple_video/fast_video.py
examples/paper/simple_video/full_video.py
examples/paper/simple_video/random_video.py
cddm-0.3.0.dist-info/LICENSE
cddm-0.3.0.dist-info/METADATA
cddm-0.3.0.dist-info/WHEEL
cddm-0.3.0.dist-info/top_level.txt
cddm-0.3.0.dist-info/RECORD
