Metadata-Version: 2.1
Name: cddm
Version: 0.3.0
Summary: Tools for cross-differential dynamic microscopy
Home-page: https://github.com/IJSComplexMatter/cddm
Author: Andrej Petelin
Author-email: andrej.petelin@gmail.com
License: UNKNOWN
Platform: UNKNOWN
Classifier: Programming Language :: Python :: 3
Classifier: License :: OSI Approved :: MIT License
Classifier: Operating System :: OS Independent
